openimis_be_tasks_management-1.4.0.dist-info/licenses/LICENSE.md
tasks_management/__init__.py
tasks_management/admin.py
tasks_management/apps.py
tasks_management/gql_mutations.py
tasks_management/gql_queries.py
tasks_management/models.py
tasks_management/schema.py
tasks_management/services.py
tasks_management/urls.py
tasks_management/validation.py
tasks_management/views.py
tasks_management/migrations/0001_initial.py
tasks_management/migrations/0002_add_task_triage_role.py
tasks_management/migrations/0003_historicaltaskexecutor_taskexecutor.py
tasks_management/migrations/0004_auto_20230628_1404.py
tasks_management/migrations/0005_add_task_perms_to_admin.py
tasks_management/migrations/0006_add_search_users_to_task_triage.py
tasks_management/migrations/0007_taskmutation.py
tasks_management/migrations/0008_auto_20240118_1510.py
tasks_management/migrations/0009_alter_historicaltask_business_data_serializer_and_more.py
tasks_management/migrations/0010_add_search_all_perms_admin.py
tasks_management/migrations/__init__.py
tasks_management/signals/__init__.py
tasks_management/signals/on_task_resolve.py
tasks_management/tests/__init__.py
tasks_management/tests/checker_logic_service_tests.py
tasks_management/tests/data.py
tasks_management/tests/task_event_tests.py
tasks_management/tests/task_group_service_tests.py
tasks_management/tests/task_service_tests.py
openimis_be_tasks_management-1.4.0.dist-info/METADATA
openimis_be_tasks_management-1.4.0.dist-info/WHEEL
openimis_be_tasks_management-1.4.0.dist-info/top_level.txt
openimis_be_tasks_management-1.4.0.dist-info/RECORD
